{
  "reportDate": "2025-12-15",
  "latestEntry": {
    "surveyDate": "2025-12-14",
    "batch1": {
      "trays": 16,
      "eggs": 8,
      "broken": 1,
      "totalEggs": 488,
      "layingPercentage": "84.00"
    },
    "batch2": {
      "trays": 31,
      "eggs": 12,
      "broken": 2,
      "totalEggs": 942,
      "layingPercentage": "88.00"
    },
    "combined": {
      "totalEggsEntry": 1430,
      "layingPercentageDaily": "87.00"
    },
    "submittedAt": "2025-12-14 17:44"
  },
  "overallTotals": {
    "batch1": {
      "trays": 3382,
      "eggs": 2097,
      "broken": 131
    },
    "batch2": {
      "trays": 531,
      "eggs": 305,
      "broken": 31
    },
    "combined": {
      "totalEggsAllRecords": 119792,
      "totalTraysCalculated": 3993,
      "remainingEggs": 2
    }
  },
  "recentTotals": {
    "sevenDay": 2845,
    "thirtyDay": 23830
  },
  "rollingAverages": {
    "yesterday": {
      "average": 1430,
      "trend": "❌"
    },
    "threeDay": {
      "average": 1422,
      "trend": "❌"
    },
    "sevenDay": {
      "average": 1422,
      "trend": "❌"
    },
    "thirtyDay": {
      "average": 1134,
      "trend": "❌"
    }
  }
}
